wagtail_paginated_subpages/__init__.py
wagtail_paginated_subpages/apps.py
wagtail_paginated_subpages/settings.py
wagtail_paginated_subpages/mixins/__init__.py
wagtail_paginated_subpages/mixins/pagination.py
wagtail_paginated_subpages/templates/wagtail_paginated_subpages/pagination.html
wagtail_paginated_subpages/templates/wagtail_paginated_subpages/pagination_meta.html
wagtail_paginated_subpages/templatetags/__init__.py
wagtail_paginated_subpages/templatetags/wagtail_paginated_tags.py
wagtail_paginated_subpages-0.6.1.dist-info/DESCRIPTION.rst
wagtail_paginated_subpages-0.6.1.dist-info/METADATA
wagtail_paginated_subpages-0.6.1.dist-info/RECORD
wagtail_paginated_subpages-0.6.1.dist-info/WHEEL
wagtail_paginated_subpages-0.6.1.dist-info/metadata.json
wagtail_paginated_subpages-0.6.1.dist-info/top_level.txt
