Metadata-Version: 2.0
Name: wagtail-paginated-subpages
Version: 0.6.1
Summary: A pagination plugin app for django wagtail CMS
Home-page: https://github.com/Designer023/Wagtail-Paginated-Subpages
Author: Carl Topham
Author-email: carl@carl-topham.com
License: MIT License
Platform: UNKNOWN
Classifier: Environment :: Web Environment
Classifier: Framework :: Django
Classifier: Framework :: Django :: 1.11
Classifier: Intended Audience :: Developers
Classifier: License :: OSI Approved :: MIT License
Classifier: Operating System :: OS Independent
Classifier: Programming Language :: Python
Classifier: Programming Language :: Python :: 3
Classifier: Programming Language :: Python :: 3.4
Classifier: Programming Language :: Python :: 3.5
Classifier: Topic :: Internet :: WWW/HTTP
Classifier: Topic :: Internet :: WWW/HTTP :: Dynamic Content
Requires-Dist: django (<1.12,>=1.11)
Requires-Dist: wagtail (<1.14,>=1.13)
